Metadata-Version: 2.1
Name: KeiAPI
Version: 1.0.1
Summary: Kei is an unofficial, Pure Python API for gogoanime2.org.
Home-page: https://github.com/onkardahale/kei
Author: Onkar Dahale
Author-email: dahaleonkar@gmail.com
License: UNKNOWN
Project-URL: Bug Tracker, https://github.com/onkardahale/kei/issues
Keywords: api,BeautifulSoup,gogoanime,webscraper,JSON
Platform: UNKNOWN
Classifier: Operating System :: OS Independent
Classifier: Programming Language :: Python :: 3.9
Classifier: License :: OSI Approved :: MIT License
Requires-Python: >=3.9.5
